{
  "upload_id": "90b572864fe2437497c3e0c2c03d699b",
  "filename": "orders.csv",
  "stored_path": "data/uploads/90b572864fe2437497c3e0c2c03d699b_orders.csv",
  "delimiter": ",",
  "encoding": "utf-8",
  "columns": [
    "order_id",
    "order_date",
    "customer_id",
    "sku",
    "quantity",
    "unit_price",
    "shipment_status",
    "store_code"
  ],
  "mapping": {
    "order_id": "order_id",
    "order_date": "order_date",
    "customer_id": "customer_id",
    "sku": "sku",
    "quantity": "quantity",
    "unit_price": "unit_price",
    "store_code": "store_code"
  },
  "mapping_summary": {
    "mapped_columns": {
      "order_id": "order_id",
      "order_date": "order_date",
      "customer_id": "customer_id",
      "sku": "sku",
      "quantity": "quantity",
      "unit_price": "unit_price",
      "store_code": "store_code"
    },
    "unmapped_columns": [],
    "required_missing": [],
    "aliases_applied": {
      "shipment_status": "shipment_status"
    }
  },
  "validation_summary": {
    "upload_id": "90b572864fe2437497c3e0c2c03d699b",
    "filename": "orders.csv",
    "row_count": 3,
    "mapped_columns": {
      "order_id": "order_id",
      "order_date": "order_date",
      "customer_id": "customer_id",
      "sku": "sku",
      "quantity": "quantity",
      "unit_price": "unit_price",
      "store_code": "store_code"
    },
    "warnings": [],
    "blocking_errors": [],
    "can_import": true
  },
  "import_summary": {
    "source_id": 1,
    "source_name": "easy_csv_orders_90b57286",
    "import_job_id": 1,
    "sync_run_id": 1,
    "rows_extracted": 3,
    "rows_loaded": 3,
    "source_status": "ready"
  },
  "transform_summary": {
    "upload_id": "90b572864fe2437497c3e0c2c03d699b",
    "filename": "orders.csv",
    "transform_run_id": "tr_f52947d8ad8c",
    "input_row_count": 3,
    "output_row_count": 3,
    "total_orders": 3,
    "total_quantity": 7.0,
    "total_revenue": 62.0,
    "daily_sales": [
      {
        "sales_date": "2026-03-20",
        "order_count": 1,
        "total_quantity": 2.0,
        "total_revenue": 21.0
      },
      {
        "sales_date": "2026-03-21",
        "order_count": 1,
        "total_quantity": 1.0,
        "total_revenue": 20.0
      },
      {
        "sales_date": "2026-03-22",
        "order_count": 1,
        "total_quantity": 4.0,
        "total_revenue": 21.0
      }
    ],
    "artifact_path": "data/artifacts/transforms/90b572864fe2437497c3e0c2c03d699b_tr_f52947d8ad8c.json"
  },
  "dashboard_summary": {
    "upload_id": "90b572864fe2437497c3e0c2c03d699b",
    "filename": "orders.csv",
    "dashboard_id": "dash_97f30fc7312c",
    "dashboard_title": "Starter KPI dashboard · orders.csv",
    "dashboard_url": "/easy-csv/90b572864fe2437497c3e0c2c03d699b/dashboard/view",
    "artifact_path": "data/artifacts/dashboards/90b572864fe2437497c3e0c2c03d699b_dash_97f30fc7312c.json",
    "cards": [
      {
        "title": "Total orders",
        "value": "3",
        "description": "Unique orders in the starter transform output."
      },
      {
        "title": "Total quantity",
        "value": "7.00",
        "description": "Units sold across the loaded dataset."
      },
      {
        "title": "Total revenue",
        "value": "62.00",
        "description": "Quantity multiplied by unit price."
      },
      {
        "title": "Sales days",
        "value": "3",
        "description": "Distinct daily buckets available for simple trend views."
      }
    ]
  },
  "forecast_summary": {
    "upload_id": "90b572864fe2437497c3e0c2c03d699b",
    "filename": "orders.csv",
    "forecast_run_id": "fc_38f9580513de",
    "baseline_method": "daily_average_baseline",
    "base_daily_orders": 1.0,
    "base_daily_units": 2.33,
    "base_daily_revenue": 20.67,
    "horizons": [
      {
        "horizon_days": 7,
        "projected_orders": 7.0,
        "projected_units": 16.31,
        "projected_revenue": 144.69
      },
      {
        "horizon_days": 14,
        "projected_orders": 14.0,
        "projected_units": 32.62,
        "projected_revenue": 289.38
      },
      {
        "horizon_days": 30,
        "projected_orders": 30.0,
        "projected_units": 69.9,
        "projected_revenue": 620.1
      }
    ],
    "daily_forecast": [
      {
        "forecast_date": "2026-03-23",
        "projected_units": 2.33,
        "projected_revenue": 20.67
      },
      {
        "forecast_date": "2026-03-24",
        "projected_units": 2.33,
        "projected_revenue": 20.67
      },
      {
        "forecast_date": "2026-03-25",
        "projected_units": 2.33,
        "projected_revenue": 20.67
      },
      {
        "forecast_date": "2026-03-26",
        "projected_units": 2.33,
        "projected_revenue": 20.67
      },
      {
        "forecast_date": "2026-03-27",
        "projected_units": 2.33,
        "projected_revenue": 20.67
      },
      {
        "forecast_date": "2026-03-28",
        "projected_units": 2.33,
        "projected_revenue": 20.67
      },
      {
        "forecast_date": "2026-03-29",
        "projected_units": 2.33,
        "projected_revenue": 20.67
      }
    ],
    "artifact_path": "data/artifacts/forecasts/90b572864fe2437497c3e0c2c03d699b_fc_38f9580513de.json"
  }
}